AUTHORS.rst
HISTORY.rst
LICENSE
MANIFEST.in
Makefile
README.rst
requirements.txt
requirements_dev.txt
setup.cfg
setup.py
rooki/__init__.py
rooki/client.py
rooki/config.py
rooki/default.cfg
rooki/operators.py
rooki/results.py
rooki.egg-info/PKG-INFO
rooki.egg-info/SOURCES.txt
rooki.egg-info/dependency_links.txt
rooki.egg-info/not-zip-safe
rooki.egg-info/requires.txt
rooki.egg-info/top_level.txt
tests/test_config.py
tests/test_rooki.py
tests/test_workflow.py