Metadata-Version: 2.4
Name: rooki
Version: 0.6.4
Summary: A client for roocs climate data operations service.
Home-page: https://github.com/roocs/rooki
Author: Carsten Ehbrecht
Author-email: ehbrecht@dkrz.de
License: BSD - see LICENSE file in top-level package directory
Keywords: rooki
Classifier: Development Status :: 5 - Production/Stable
Classifier: Environment :: Console
Classifier: Environment :: Web Environment
Classifier: Intended Audience :: End Users/Desktop
Classifier: Intended Audience :: Developers
Classifier: Intended Audience :: Science/Research
Classifier: License :: OSI Approved :: BSD License
Classifier: Natural Language :: English
Classifier: Operating System :: Microsoft :: Windows
Classifier: Operating System :: POSIX :: Linux
Classifier: Programming Language :: Python
Classifier: Programming Language :: Python :: 3
Classifier: Programming Language :: Python :: 3.9
Classifier: Programming Language :: Python :: 3.10
Classifier: Programming Language :: Python :: 3.11
Classifier: Topic :: Security
Classifier: Topic :: Internet
Classifier: Topic :: Scientific/Engineering
Classifier: Topic :: System :: Distributed Computing
Classifier: Topic :: Software Development :: Libraries :: Python Modules
Requires-Python: >=3.9.0
License-File: LICENSE
License-File: AUTHORS.rst
Requires-Dist: Click>=6.0
Requires-Dist: birdhouse-birdy<0.9.0,>=0.8.2
Requires-Dist: netCDF4>=1.5
Requires-Dist: xarray>=0.16
Requires-Dist: cf-xarray
Requires-Dist: beautifulsoup4>=4.9.1
Requires-Dist: pymetalink>=6.2
Dynamic: author
Dynamic: author-email
Dynamic: classifier
Dynamic: description
Dynamic: description-content-type
Dynamic: home-page
Dynamic: keywords
Dynamic: license
Dynamic: license-file
Dynamic: requires-dist
Dynamic: requires-python
Dynamic: summary
